odoo/addons/ssi_sprint_backoffice_account_move/README.rst
odoo/addons/ssi_sprint_backoffice_account_move/__init__.py
odoo/addons/ssi_sprint_backoffice_account_move/__manifest__.py
odoo/addons/ssi_sprint_backoffice_account_move/models/__init__.py
odoo/addons/ssi_sprint_backoffice_account_move/models/account_move.py
odoo/addons/ssi_sprint_backoffice_account_move/models/account_move_cancel_payment_history.py
odoo/addons/ssi_sprint_backoffice_account_move/models/account_move_line.py
odoo/addons/ssi_sprint_backoffice_account_move/models/account_move_update_payment_history.py
odoo/addons/ssi_sprint_backoffice_account_move/models/account_move_update_print_info.py
odoo/addons/ssi_sprint_backoffice_account_move/models/sprint_backoffice_backend.py
odoo/addons/ssi_sprint_backoffice_account_move/security/ir.model.access.csv
odoo/addons/ssi_sprint_backoffice_account_move/static/description/icon.png
odoo/addons/ssi_sprint_backoffice_account_move/views/account_move_views.xml
odoo/addons/ssi_sprint_backoffice_account_move/views/sprint_backoffice_backend_views.xml
odoo14_addon_ssi_sprint_backoffice_account_move-14.0.2.2.0.dist-info/METADATA
odoo14_addon_ssi_sprint_backoffice_account_move-14.0.2.2.0.dist-info/WHEEL
odoo14_addon_ssi_sprint_backoffice_account_move-14.0.2.2.0.dist-info/top_level.txt
odoo14_addon_ssi_sprint_backoffice_account_move-14.0.2.2.0.dist-info/RECORD
